corehost/up.py
corehost/INSTANCE/state.py
corehost/KEYS/seed.py
corehost/KEYS/pool/block.py
corehost/MODE/debug_core.py
corehost/MODE/debug_keys.py
corehost/MODE/debug_steps.py
corehost/MODE/facilities.py
corehost/MODE/settings.py
corehost-0.0.1.dist-info/LICENSE
corehost-0.0.1.dist-info/METADATA
corehost-0.0.1.dist-info/WHEEL
corehost-0.0.1.dist-info/top_level.txt
corehost-0.0.1.dist-info/RECORD
