Metadata-Version: 2.1
Name: corehost
Version: 0.0.1
Summary: The client-side program to interact with CORE.HOST
Author-email: "CORE.HOST, LLC." <Operator@CORE.HOST>
Project-URL: Homepage, https://github.com/corehost/corehost
Project-URL: Bug Tracker, https://github.com/corehost/corehost/issues
Keywords: C.ORE,AI,CORE.HOST,corehost
Requires-Python: >=3.12
License-File: LICENSE
